map_ukraine/__init__.py
map_ukraine/map.py
map_ukraine/map_data/UKR_admin0.csv
map_ukraine/map_data/UKR_admin0.geojson
map_ukraine/map_data/UKR_admin1.csv
map_ukraine/map_data/UKR_admin1.geojson
map_ukraine/map_data/UKR_admin2.csv
map_ukraine/map_data/UKR_admin2.geojson
map_ukraine-0.1.dist-info/METADATA
map_ukraine-0.1.dist-info/WHEEL
map_ukraine-0.1.dist-info/top_level.txt
map_ukraine-0.1.dist-info/RECORD
