Metadata-Version: 2.1
Name: map-ukraine
Version: 0.1
Summary: UNKNOWN
Home-page: UNKNOWN
Author: Igor Tereshchenko
Author-email: tereshchenko.igor@gmail.com
License: UNKNOWN
Platform: UNKNOWN
Classifier: Programming Language :: Python :: 3
Classifier: License :: OSI Approved :: MIT License
Classifier: Operating System :: OS Independent
Requires-Dist: attrs (==21.2.0)
Requires-Dist: bleach (==4.1.0)
Requires-Dist: branca (==0.4.2)
Requires-Dist: certifi (==2021.5.30)
Requires-Dist: cffi (==1.14.6)
Requires-Dist: charset-normalizer (==2.0.6)
Requires-Dist: click (==8.0.1)
Requires-Dist: click-plugins (==1.1.1)
Requires-Dist: cligj (==0.7.2)
Requires-Dist: colorama (==0.4.4)
Requires-Dist: colorscale (==0.8.2)
Requires-Dist: cryptography (==3.4.8)
Requires-Dist: cycler (==0.10.0)
Requires-Dist: cykhash (==1.0.2)
Requires-Dist: Cython (==0.29.24)
Requires-Dist: docutils (==0.17.1)
Requires-Dist: Fiona (==1.8.20)
Requires-Dist: folium (==0.12.1)
Requires-Dist: geopandas (==0.9.0)
Requires-Dist: idna (==3.2)
Requires-Dist: importlib-metadata (==4.8.1)
Requires-Dist: jeepney (==0.7.1)
Requires-Dist: Jinja2 (==3.0.1)
Requires-Dist: keyring (==23.2.1)
Requires-Dist: kiwisolver (==1.3.2)
Requires-Dist: MarkupSafe (==2.0.1)
Requires-Dist: matplotlib (==3.4.3)
Requires-Dist: munch (==2.5.0)
Requires-Dist: numpy (==1.21.2)
Requires-Dist: opencv-python (==4.5.3.56)
Requires-Dist: osmium (==3.2.0)
Requires-Dist: packaging (==21.0)
Requires-Dist: pandas (==1.3.3)
Requires-Dist: Pillow (==8.3.2)
Requires-Dist: pkginfo (==1.7.1)
Requires-Dist: plotly (==5.3.1)
Requires-Dist: pycparser (==2.20)
Requires-Dist: pygeos (==0.10.2)
Requires-Dist: Pygments (==2.10.0)
Requires-Dist: pyparsing (==2.4.7)
Requires-Dist: pyproj (==3.2.1)
Requires-Dist: pyrobuf (==0.9.3)
Requires-Dist: pyrosm (==0.6.0)
Requires-Dist: python-dateutil (==2.8.2)
Requires-Dist: python-rapidjson (==1.4)
Requires-Dist: pytz (==2021.1)
Requires-Dist: readme-renderer (==29.0)
Requires-Dist: requests (==2.26.0)
Requires-Dist: requests-toolbelt (==0.9.1)
Requires-Dist: rfc3986 (==1.5.0)
Requires-Dist: SecretStorage (==3.3.1)
Requires-Dist: Shapely (==1.7.1)
Requires-Dist: six (==1.16.0)
Requires-Dist: tenacity (==8.0.1)
Requires-Dist: tqdm (==4.62.3)
Requires-Dist: twine (==3.4.2)
Requires-Dist: typing-extensions (==3.10.0.2)
Requires-Dist: urllib3 (==1.26.6)
Requires-Dist: webencodings (==0.5.1)
Requires-Dist: zipp (==3.5.0)
